kaczmarz/__init__.py
kaczmarz/_abc.py
kaczmarz/_normalize.py
kaczmarz/_utils.py
kaczmarz/_variants.py
kaczmarz_algorithms-0.8.1.dist-info/LICENSE
kaczmarz_algorithms-0.8.1.dist-info/METADATA
kaczmarz_algorithms-0.8.1.dist-info/WHEEL
kaczmarz_algorithms-0.8.1.dist-info/top_level.txt
kaczmarz_algorithms-0.8.1.dist-info/RECORD
