Metadata-Version: 2.1
Name: kaczmarz-algorithms
Version: 0.8.1
Summary: Variants of the Kaczmarz algorithm for solving linear systems.
Home-page: https://github.com/jdmoorman/kaczmarz-algorithms
Author: Jacob Moorman
Author-email: jacob@moorman.me
License: MIT
Keywords: kaczmarz
Platform: UNKNOWN
Classifier: Development Status :: 4 - Beta
Classifier: Intended Audience :: Science/Research 
Classifier: License :: OSI Approved :: MIT License
Classifier: Natural Language :: English
Classifier: Programming Language :: Python
Classifier: Programming Language :: Python :: 3
Classifier: Programming Language :: Python :: 3 :: Only
Classifier: Programming Language :: Python :: 3.6
Classifier: Programming Language :: Python :: 3.7
Classifier: Programming Language :: Python :: 3.8
Classifier: Topic :: Scientific/Engineering
Requires-Python: >=3.6
License-File: LICENSE
Requires-Dist: numpy
Requires-Dist: scipy
Provides-Extra: all
Requires-Dist: numpy ; extra == 'all'
Requires-Dist: scipy ; extra == 'all'
Requires-Dist: pytest ; extra == 'all'
Requires-Dist: pytest-cov ; extra == 'all'
Requires-Dist: pytest-raises ; extra == 'all'
Requires-Dist: pytest-allclose ; extra == 'all'
Requires-Dist: pytest-timeout ; extra == 'all'
Requires-Dist: sphinx ; extra == 'all'
Requires-Dist: sphinx-rtd-theme ; extra == 'all'
Requires-Dist: m2r ; extra == 'all'
Requires-Dist: pytest-runner ; extra == 'all'
Requires-Dist: pre-commit ; extra == 'all'
Requires-Dist: bump2version (>=1.0.0) ; extra == 'all'
Requires-Dist: ipython (>=7.5.0) ; extra == 'all'
Requires-Dist: tox (>=3.5.2) ; extra == 'all'
Requires-Dist: twine (>=1.13.0) ; extra == 'all'
Requires-Dist: wheel (>=0.33.1) ; extra == 'all'
Provides-Extra: dev
Requires-Dist: pytest ; extra == 'dev'
Requires-Dist: pytest-cov ; extra == 'dev'
Requires-Dist: pytest-raises ; extra == 'dev'
Requires-Dist: pytest-allclose ; extra == 'dev'
Requires-Dist: pytest-timeout ; extra == 'dev'
Requires-Dist: sphinx ; extra == 'dev'
Requires-Dist: sphinx-rtd-theme ; extra == 'dev'
Requires-Dist: m2r ; extra == 'dev'
Requires-Dist: pytest-runner ; extra == 'dev'
Requires-Dist: pre-commit ; extra == 'dev'
Requires-Dist: bump2version (>=1.0.0) ; extra == 'dev'
Requires-Dist: ipython (>=7.5.0) ; extra == 'dev'
Requires-Dist: tox (>=3.5.2) ; extra == 'dev'
Requires-Dist: twine (>=1.13.0) ; extra == 'dev'
Requires-Dist: wheel (>=0.33.1) ; extra == 'dev'
Provides-Extra: docs
Requires-Dist: sphinx ; extra == 'docs'
Requires-Dist: sphinx-rtd-theme ; extra == 'docs'
Requires-Dist: m2r ; extra == 'docs'
Provides-Extra: setup
Requires-Dist: pytest-runner ; extra == 'setup'
Provides-Extra: test
Requires-Dist: pytest ; extra == 'test'
Requires-Dist: pytest-cov ; extra == 'test'
Requires-Dist: pytest-raises ; extra == 'test'
Requires-Dist: pytest-allclose ; extra == 'test'
Requires-Dist: pytest-timeout ; extra == 'test'
